quickcnn/__init__.py
quickcnn/ckpt_callback.py
quickcnn/data_split.py
quickcnn/hist_callback.py
quickcnn/retrain.py
quickcnn/setup_tbc.py
quickcnn/tbc_callback.py
quickcnn/write_result.py
quickcnn-0.0.12.dist-info/DESCRIPTION.rst
quickcnn-0.0.12.dist-info/METADATA
quickcnn-0.0.12.dist-info/RECORD
quickcnn-0.0.12.dist-info/WHEEL
quickcnn-0.0.12.dist-info/metadata.json
quickcnn-0.0.12.dist-info/top_level.txt
