Metadata-Version: 2.0
Name: quickcnn
Version: 0.0.12
Summary: ConvNet architectures on Google-Colaboratory
Home-page: https://github.com/CG1507/quickcnn
Author: Ghanshyam Chodavadiya
Author-email: g8ghanshym@gmail.com
License: UNKNOWN
Platform: UNKNOWN
Classifier: Programming Language :: Python :: 3
Classifier: License :: OSI Approved :: MIT License
Classifier: Operating System :: OS Independent
